abn_lookup-0.1.0.dist-info/licenses/LICENSE
abnlookup/__init__.py
abnlookup/client.py
abnlookup/endpoints.py
abnlookup/exceptions.py
abnlookup/models.py
abn_lookup-0.1.0.dist-info/METADATA
abn_lookup-0.1.0.dist-info/WHEEL
abn_lookup-0.1.0.dist-info/top_level.txt
abn_lookup-0.1.0.dist-info/RECORD
