Metadata-Version: 2.4
Name: abn-lookup
Version: 0.1.0
Summary: A Python wrapper for the Australian Business Register (ABR) ABN Lookup API.
Author-email: Santiago <santiago@whitestreak.io>
License: MIT
Project-URL: Homepage, https://github.com/WhiteStreakTechnologies/abn-lookup
Requires-Python: >=3.8
License-File: LICENSE
Dynamic: license-file
